naps-0.1.dev526.dist-info/METADATA
naps-0.1.dev526.dist-info/WHEEL
naps-0.1.dev526.dist-info/entry_points.txt
naps-0.1.dev526.dist-info/licenses/LICENSE
naps/__init__.py
naps/cores/__init__.py
naps/cores/axi/__init__.py
naps/cores/axi/axi_endpoint.py
naps/cores/axi/full_to_lite.py
naps/cores/axi/interconnect.py
naps/cores/axi/peripheral_connector.py
naps/cores/axi/sim_util.py
naps/cores/axi/specification.pdf
naps/cores/axi/specification_notes.org
naps/cores/axi/stream_reader.py
naps/cores/axi/stream_reader_test.py
naps/cores/axi/stream_writer.py
naps/cores/axi/stream_writer_test.py
naps/cores/axi/zynq_util.py
naps/cores/cmv12k/__init__.py
naps/cores/cmv12k/cmv12k_rx.py
naps/cores/cmv12k/cmv12k_spi.py
naps/cores/cmv12k/pixel_remapper.py
naps/cores/cmv12k/s7_phy.py
naps/cores/compression/__init__.py
naps/cores/compression/bit_stuffing.py
naps/cores/compression/bit_stuffing_test.py
naps/cores/compression/encoding_space.py
naps/cores/compression/huffman_encoder.py
naps/cores/compression/huffman_encoder_test.py
naps/cores/compression/rle.py
naps/cores/compression/rle_test.py
naps/cores/debug/__init__.py
naps/cores/debug/blink_debug.py
naps/cores/debug/clocking_debug.py
naps/cores/debug/fsm_status_reg.py
naps/cores/debug/ila.py
naps/cores/debug/ila_test.py
naps/cores/debug/packet_console.py
naps/cores/debug/packet_console_test.py
naps/cores/debug/tracer.py
naps/cores/dram_packet_ringbuffer/__init__.py
naps/cores/dram_packet_ringbuffer/cpu_if.py
naps/cores/dram_packet_ringbuffer/stream_if.py
naps/cores/dram_packet_ringbuffer/stream_if_test.py
naps/cores/ft601/__init__.py
naps/cores/ft601/ft601_perf_debug.py
naps/cores/ft601/ft601_stream_sink.py
naps/cores/ft601/ft601_stream_sink_test.py
naps/cores/ft601/ft60x_legalizer.py
naps/cores/hdmi/InfoFrame.py
naps/cores/hdmi/__init__.py
naps/cores/hdmi/cvt_python.py
naps/cores/hdmi/cvt_subprocess.py
naps/cores/hdmi/hdmispecification13a.pdf
naps/cores/hdmi/parse_modeline.py
naps/cores/hdmi/rx/__init__.py
naps/cores/hdmi/rx/hdmi_rx.py
naps/cores/hdmi/rx/tmds_decoder.py
naps/cores/hdmi/tmds.py
naps/cores/hdmi/tmds_test.py
naps/cores/hdmi/tx/__init__.py
naps-0.1.dev526.dist-info/RECORD
