Metadata-Version: 2.1
Name: naps
Version: 0.1.dev526
Summary: naps - The Relaxed Amaranth Packages Collection
Keywords: amaranth apertus fpga gateware video camera
Author-Email: Robin Heinemann <robin.ole.heinemann+naps@gmail.com>, Jaro Habiger <jarohabiger@googlemail.com>
License:                     GNU GENERAL PUBLIC LICENSE
Project-URL: Homepage, https://github.com/apertus-open-source-cinema/naps
Project-URL: Documentation, https://docs.niemo.de/naps/commit/97936aa85819969db27a799a5c23063dfb5cf00d
Project-URL: Bug Tracker, https://github.com/apertus-open-source-cinema/naps/issues
Requires-Python: >=3.11
Requires-Dist: amaranth==0.5.5
Requires-Dist: huffman
Requires-Dist: paramiko
Provides-Extra: publish
Requires-Dist: twine>=4.0.2; extra == "publish"
